Metadata-Version: 2.1
Name: bedspread
Version: 0.0.1
Summary: Bed Spread: an Expression-Oriented Code-in-Database System
Home-page: https://github.com/kjosib/bedspread
Author: Ian Kjos
Author-email: kjosib@gmail.com
License: MIT
Platform: UNKNOWN
Classifier: Programming Language :: Python :: 3
Classifier: License :: OSI Approved :: MIT License
Classifier: Operating System :: OS Independent
Classifier: Development Status :: 2 - Pre-Alpha
Classifier: Intended Audience :: Developers
Classifier: Intended Audience :: Education
Classifier: Topic :: Software Development :: Interpreters
Classifier: Topic :: Software Development :: Libraries
Classifier: Topic :: Education
Classifier: Environment :: Console
Requires-Python: >=3.7
License-File: LICENSE
